<?xml version="1.0" encoding="utf-8"?>
<Afflictions>

				<!-- DAMAGE AFFLICTIONS -->
		<!-- NO EYES -->
	<Affliction name="" identifier="noeye" description="" limbspecific="true" indicatorlimb="Head" showiconthreshold="1" showinhealthscannerthreshold="1" maxstrength="2" type="gaze" causeofdeathdescription="" selfcauseofdeathdescription="" isbuff="false" healableinmedicalclinic="false" iconcolors="84,211,211,255;84,211,211,255">
	
		<Effect minstrength="0" maxstrength="2" minscreendistort="15" maxscreendistort="15" minscreenblur="100" maxscreenblur="100" minradialdistort="1" maxradialdistort="1" minchromaticaberration="200" maxchromaticaberration="200" minskillmultiplier="0.25" maxskillmultiplier="0.25" maxspeedmultiplier="0.5"> 
		
			<StatusEffect target="Character">
				<TriggerAnimation Type="Walk" filename="DrunkenWalk" priority="6" ExpectedSpecies="Human" />
				<TriggerAnimation Type="Run" filename="DrunkenRun" priority="6" ExpectedSpecies="Human" />
			</StatusEffect>
			
		</Effect>
		
		<AfflictionOverlay texture="%ModDir%/Textures/Overlays/blackoverlay.png" />
		
		<icon texture="%ModDir%/Textures/AfflictionIcons.png" sourcerect="0,256,128,128"  origin="0,0" />
		
	</Affliction>
  
		<!-- EYES DEAD -->
	<Affliction name="" identifier="eyesdead" description="" limbspecific="true" indicatorlimb="Head" showiconthreshold="1" showinhealthscannerthreshold="1" maxstrength="2" causeofdeathdescription="" selfcauseofdeathdescription="" isbuff="false" healableinmedicalclinic="false" iconcolors="255,0,0,255;255,0,0,255">
	
		<Effect minstrength="0" maxstrength="2" minscreendistort="15" maxscreendistort="15" minscreenblur="100" maxscreenblur="100" minradialdistort="1" maxradialdistort="1" minchromaticaberration="200" maxchromaticaberration="200" minskillmultiplier="0.25" maxskillmultiplier="0.25" maxspeedmultiplier="0.5">
	
			<StatusEffect target="Character">
				<TriggerAnimation Type="Walk" filename="DrunkenWalk" priority="6" ExpectedSpecies="Human" />
				<TriggerAnimation Type="Run" filename="DrunkenRun" priority="6" ExpectedSpecies="Human" />
			</StatusEffect>
		
		</Effect>
		
		<AfflictionOverlay texture="%ModDir%/Textures/Overlays/blind.png" />
		
		<icon texture="%ModDir%/Textures/AfflictionIcons.png" sourcerect="0,384,128,128"  origin="0,0" />
		
	</Affliction>
  
		<!-- EYE ONE -->
	<Affliction name="" identifier="eyeone" description=""  limbspecific="true" indicatorlimb="Head" showiconthreshold="0" maxstrength="2" showinhealthscannerthreshold="100" iconcolors="255,80,0,255;255,80,0,255">
		<icon texture="%ModDir%/Textures/AfflictionIcons.png" sourcerect="640,0,128,128"  origin="0,0" />
	</Affliction>
	
		<!-- LEFT EYE GONE -->
	<Affliction name="" identifier="lefteyegone" description=""  limbspecific="true" indicatorlimb="Head" showiconthreshold="100" showinhealthscannerthreshold="100" maxstrength="2">
		<Effect minstrength="0" maxstrength="2"/>
		<AfflictionOverlay texture="%ModDir%/Textures/Overlays/leftblind.png"/>
	</Affliction>
	
		<!-- RIGHT EYE GONE -->
	<Affliction name="" identifier="righteyegone" description=""  limbspecific="true" indicatorlimb="Head" showiconthreshold="100" showinhealthscannerthreshold="100" maxstrength="2">
		<Effect minstrength="0" maxstrength="2"/>
		<AfflictionOverlay texture="%ModDir%/Textures/Overlays/rightblind.png"/>
	</Affliction>
  
		<!-- EYE DAMAGE -->
	<Affliction name="" identifier="eyedamage" description="" limbspecific="true" indicatorlimb="Head" showiconthreshold="25" showinhealthscannerthreshold="10" maxstrength="100" targets="human" type="gaze" causeofdeathdescription="" selfcauseofdeathdescription="" isbuff="false" healableinmedicalclinic="false" iconcolors="50,50,0,255;255,50,50,255">
		<Effect minstrength="0" maxstrength="51" minscreendistort="0" maxscreendistort="0.5" minscreenblur="0" maxscreenblur="0" minradialdistort="0" maxradialdistort="0.1" minchromaticaberration="0" maxchromaticaberration="1" minskillmultiplier="1.0" maxskillmultiplier="0.9"></Effect>
		<Effect minstrength="52" maxstrength="100" minscreendistort="0.5" maxscreendistort="15" minscreenblur="0.4" maxscreenblur="100" minradialdistort="0.1" maxradialdistort="1" minchromaticaberration="1" maxchromaticaberration="200" minskillmultiplier="0.8" maxskillmultiplier="0.35" minspeedmultiplier="1" maxspeedmultiplier="0.6"></Effect>
		<icon texture="%ModDir%/Textures/AfflictionIcons.png" sourcerect="384,0,128,128"  origin="0,0" />
	</Affliction>
  
		<!-- EYE SHOCK -->
	<Affliction name="" identifier="eyeshock" description="" limbspecific="true" indicatorlimb="Head" showiconthreshold="80" showinhealthscannerthreshold="20" maxstrength="100" targets="human" type="gaze" causeofdeathdescription="" selfcauseofdeathdescription="" isbuff="false" healableinmedicalclinic="false" iconcolors="0,0,0,255;255,100,0,255">
		<icon texture="%ModDir%/Textures/AfflictionIcons.png" sourcerect="896,0,128,128"  origin="0,0" />
	</Affliction>
  
		<!-- EYE DROPS -->
	<Affliction name="" identifier="eyedrop" description="" limbspecific="true" indicatorlimb="Head" showiconthreshold="0" showinhealthscannerthreshold="0" maxstrength="100" targets="human" type="gaze" causeofdeathdescription="" selfcauseofdeathdescription="" isbuff="true" healableinmedicalclinic="false" iconcolors="101, 242, 53,255;101, 242, 53,255">
		<icon texture="%ModDir%/Textures/AfflictionIcons.png" sourcerect="512,0,128,128"  origin="0,0" />
	</Affliction>
 
		<!-- VISION SICKNESS -->
	<Affliction name="" identifier="eyesickness" description="" limbspecific="true" indicatorlimb="Head" showiconthreshold="20" showinhealthscannerthreshold="0" maxstrength="100" causeofdeathdescription="" selfcauseofdeathdescription="" isbuff="false" healableinmedicalclinic="false" iconcolors="211,211,84,255;211,100,20,255">
		<Effect minstrength="0" maxstrength="70" minscreendistort="0" maxscreendistort="0.5" minscreenblur="0" maxscreenblur="0.4" minradialdistort="0" maxradialdistort="0.1" minchromaticaberration="0" maxchromaticaberration="1" minskillmultiplier="1.0" maxskillmultiplier="0.8" strengthchange="-0.4"></Effect>
		<Effect minstrength="70" maxstrength="100" minscreendistort="0.5" maxscreendistort="1" minscreenblur="0.4" maxscreenblur="0.5" minradialdistort="0.1" maxradialdistort="0.2" minchromaticaberration="1" maxchromaticaberration="2" minskillmultiplier="1" maxskillmultiplier="0.5" strengthchange="-1" minspeedmultiplier="1" maxspeedmultiplier="0.8"></Effect>
		<icon texture="%ModDir%/Textures/AfflictionIcons.png" sourcerect="768,0,128,128"  origin="0,0" />
	</Affliction>
  
		<!-- EYE CATARACT-->
	<Affliction name="" identifier="eyecataract" description="" limbspecific="true" indicatorlimb="Head" showiconthreshold="80" showinhealthscannerthreshold="20" maxstrength="100" isbuff="false" healableinmedicalclinic="false" iconcolors="250,211,211,255;250,211,211,255">
		<Effect minstrength="20" maxstrength="100" minscreendistort="0" maxscreendistort="0.2" minscreenblur="0" maxscreenblur="0.7" minradialdistort="0" maxradialdistort="0" minchromaticaberration="0" maxchromaticaberration="0.1" minskillmultiplier="1.0" maxskillmultiplier="0.9"></Effect>
		<icon texture="%ModDir%/Textures/AfflictionIcons.png" sourcerect="256,0,128,128"  origin="0,0" />
	</Affliction>
	
				
				<!-- SURGERY AFFLICTIONS -->
			<!-- EYE MUSCLE -->
	<Affliction name="" identifier="eyemuscle" description=""  limbspecific="true" indicatorlimb="Head" showiconthreshold="0" maxstrength="100" isbuff="true" iconcolors="84,211,211,255;84,211,211,255">
		<Effect minstrength="0" maxstrength="100" strengthchange="-1" />
		<icon texture="%ModDir%/Textures/AfflictionIcons.png" sourcerect="896,128,128,128"  origin="0,0" />
	</Affliction>
  
		<!-- EYE GELL -->
	<Affliction name="" identifier="eyegell" description=""  limbspecific="true" indicatorlimb="Head" showiconthreshold="0" maxstrength="100" isbuff="true" iconcolors="84,211,211,255;84,211,211,255">
		<Effect minstrength="0" maxstrength="100" strengthchange="-1" />
		<icon texture="%ModDir%/Textures/AfflictionIcons.png" sourcerect="768,128,128,128" color="0,0,255,255" origin="0,0" />
	</Affliction>
	
		<!-- NERVE CONNECTION -->
	<Affliction name="" identifier="eyenerve" description=""  limbspecific="true" indicatorlimb="Head" showiconthreshold="0" maxstrength="100" isbuff="true" iconcolors="84,211,211,255;84,211,211,255">
		<Effect minstrength="0" maxstrength="100" strengthchange="-1" />
		<icon texture="%ModDir%/Textures/AfflictionIcons.png" sourcerect="896,256,128,128" color="0,0,255,255" origin="0,0" />
	</Affliction>
  
		<!-- EYE LIDS HELD -->
	<Affliction name="" identifier="eyelid" description=""  limbspecific="true" indicatorlimb="Head" showiconthreshold="0" maxstrength="100" isbuff="true" iconcolors="84,211,211,255;84,211,211,255">
		<Effect minstrength="0" maxstrength="100" strengthchange="-2" />
		<icon texture="%ModDir%/Textures/AfflictionIcons.png" sourcerect="128,256,128,128" color="0,0,255,255" origin="0,0" />
	</Affliction>
		<!-- EYE POPPED ts without table -->
  	<Affliction name="" identifier="eyepopped" description=""  limbspecific="true" indicatorlimb="Head" showiconthreshold="0" maxstrength="100" isbuff="true" iconcolors="84,211,211,255;84,211,211,255">
		<Effect minstrength="0" maxstrength="100" strengthchange="-2" minscreendistort="0.5" maxscreendistort="10" minradialdistort="0.1" maxradialdistort="1" minchromaticaberration="1" maxchromaticaberration="200" minskillmultiplier="1" maxskillmultiplier="0.25">
			<StatusEffect target="Character" comparison="and">
				<Conditional table="eq 0" sym_unconsciousness="lte 0.1" />
				<Affliction identifier="traumaticshock" amount="3" />
			</StatusEffect>
		</Effect>
		<icon texture="%ModDir%/Textures/AfflictionIcons.png" sourcerect="512,256,128,128" color="0,0,255,255" origin="0,0" />
	</Affliction>
		<!-- CORNEA INCISION ts without opioids-->
  	<Affliction name="" identifier="corneaincision" description=""  limbspecific="true" indicatorlimb="Head" showiconthreshold="0" maxstrength="100" isbuff="true" iconcolors="84,211,211,255;84,211,211,255">
		<Effect minstrength="0" maxstrength="100" strengthchange="-1" minscreenblur="0.4" maxscreenblur="0.4" minskillmultiplier="0.8" maxskillmultiplier="0.8">
			<StatusEffect target="Character" comparison="and">
			  <Conditional analgesia="lte 0.5" anesthesia="lte 0.5" afadrenaline="lte 0.5" sym_unconsciousness="lte 0.1" />
			  <Affliction identifier="traumaticshock" amount="2" />
			</StatusEffect>
		</Effect>
		<icon texture="%ModDir%/Textures/AfflictionIcons.png" sourcerect="256,256,128,128" color="0,0,255,255" origin="0,0" />
	</Affliction>
		<!-- EMULSIFICATION ts without table -->
	<Affliction name="" identifier="emulsification" description=""  limbspecific="true" indicatorlimb="Head" showiconthreshold="0" maxstrength="2" isbuff="true" iconcolors="84,211,211,255;84,211,211,255">
		<Effect minstrength="0" maxstrength="2" minscreenblur="90" maxscreenblur="90" minskillmultiplier="0.25" maxskillmultiplier="0.25">
			<StatusEffect target="Character" comparison="and">
				<Conditional table="eq 0" sym_unconsciousness="lte 0.1" />
				<Affliction identifier="traumaticshock" amount="1.5" />
			</StatusEffect>
		</Effect>
		<icon texture="%ModDir%/Textures/AfflictionIcons.png" sourcerect="384,256,128,128" color="0,0,255,255" origin="0,0" />
	</Affliction>
		<!-- LASER SURGERY -->
	<Affliction name="" identifier="lasereyesurgery" description=""  limbspecific="true" indicatorlimb="Head" showiconthreshold="0" maxstrength="100" isbuff="true" iconcolors="84,211,211,255;84,211,211,255">
		<Effect minstrength="0" maxstrength="100" />
		<icon texture="%ModDir%/Textures/AfflictionIcons.png" sourcerect="128,384,128,128" color="0,0,255,255" origin="0,0" />
	</Affliction>
  
  
				<!-- EFFECT TYPE AFFLICTIONS --> 
			<!-- BIONIC EYE -->
	<Affliction iconcolors="211,211,84,255;211,211,84,255" name="" identifier="eyebionic" description="" limbspecific="true" indicatorlimb="Head" showiconthreshold="1" showinhealthscannerthreshold="100" maxstrength="2" targets="human" type="gaze" causeofdeathdescription="" selfcauseofdeathdescription="" isbuff="true" healableinmedicalclinic="false">
		<Effect minstrength="0" maxstrength="2" minscreendistort="-3" maxscreendistort="-3" minscreenblur="-3" maxscreenblur="-3" minradialdistort="-1.5" maxradialdistort="-1.5" minchromaticaberration="-4" maxchromaticaberration="-4" minskillmultiplier="1.1" maxskillmultiplier="1.1"></Effect>
		<icon texture="%ModDir%/Textures/AfflictionIcons.png" sourcerect="256,128,128,128"  origin="0,0" />
	</Affliction>
  
  		<!-- MEDICAL HUD -->
	<Affliction identifier="medicallens" showiconthreshold="1000" showinhealthscannerthreshold="1000" limbspecific="true" indicatorlimb="Head" maxstrength="2" healableinmedicalclinic="false" />
	
			<!-- ELECTRICAL HUD -->
	<Affliction identifier="electricallens" showiconthreshold="1000" showinhealthscannerthreshold="1000" limbspecific="true" indicatorlimb="Head" maxstrength="2" healableinmedicalclinic="false" />
  
			<!-- NIGHT VISION EYE-->
	<Affliction iconcolors="42,194,47,255;42,194,47,255" name="" identifier="eyenight" description="" limbspecific="true" indicatorlimb="Head" showiconthreshold="1" showinhealthscannerthreshold="100" maxstrength="2" targets="human" type="gaze" causeofdeathdescription="" selfcauseofdeathdescription="" isbuff="true" healableinmedicalclinic="false">
		<Effect minstrength="0" maxstrength="2"/>	
		<icon texture="%ModDir%/Textures/AfflictionIcons.png" sourcerect="512,128,128,128"  origin="0,0" />
	</Affliction>
  
			<!-- INFRARED EYE -->
	<Affliction iconcolors="16,116,179,255;16,116,179,255" name="" identifier="eyeinfrared" description="" limbspecific="true" indicatorlimb="Head" showiconthreshold="1" showinhealthscannerthreshold="100" maxstrength="2" targets="human" type="gaze" causeofdeathdescription="" selfcauseofdeathdescription="" isbuff="true" healableinmedicalclinic="false">
		<Effect minstrength="0" maxstrength="2" minspeedmultiplier="1" maxspeedmultiplier="1.05">
		<StatValue stattype="WeaponsSkillBonus" value="15" />
		</Effect>
		<icon texture="%ModDir%/Textures/AfflictionIcons.png" sourcerect="0,0,128,128"  origin="0,0" />
	</Affliction>
  
			<!-- PLASTIC EYE -->
	<Affliction iconcolors="84,211,230,255;84,211,230,255" name="" identifier="eyeplastic" description="" limbspecific="true" indicatorlimb="Head" showiconthreshold="1" showinhealthscannerthreshold="100" maxstrength="2" targets="human" type="gaze" causeofdeathdescription="" selfcauseofdeathdescription="" isbuff="true" healableinmedicalclinic="false">
		<Effect minstrength="0" maxstrength="2" minscreendistort="0.8" maxscreendistort="0.8" minscreenblur="0.4" maxscreenblur="0.4" minradialdistort="0.7" maxradialdistort="0.7" minchromaticaberration="1" maxchromaticaberration="1" minskillmultiplier="0.5" maxskillmultiplier="0.5"></Effect>
		<AfflictionOverlay texture="%ModDir%/Textures/Overlays/plasticoverlay.png" />
		<icon texture="%ModDir%/Textures/AfflictionIcons.png" sourcerect="128,128,128,128"  origin="0,0" />
	</Affliction>
  
			<!-- MONSTER EYE -->
	<Affliction iconcolors="160,160,70,255;160,160,70,255" name="" identifier="eyemonster" description="" limbspecific="true" indicatorlimb="Head" showiconthreshold="1" showinhealthscannerthreshold="100" maxstrength="2" targets="human" type="gaze" causeofdeathdescription="" selfcauseofdeathdescription="" isbuff="true" healableinmedicalclinic="false">
		<Effect minstrength="0" maxstrength="2" minscreendistort="0.7" maxscreendistort="0.7" minscreenblur="0.2" maxscreenblur="0.2" minradialdistort="1" maxradialdistort="1" minchromaticaberration="0.75" maxchromaticaberration="0.75" minskillmultiplier="0.8" maxskillmultiplier="0.8"></Effect>
		<icon texture="%ModDir%/Textures/AfflictionIcons.png" sourcerect="640,128,128,128"  origin="0,0" />
	</Affliction>
  
			<!-- HUSK EYE -->
	<Affliction iconcolors="75,0,75,255;75,0,75,255" name="" identifier="eyehusk" description="" limbspecific="true" indicatorlimb="Head" showiconthreshold="1" showinhealthscannerthreshold="100" maxstrength="2" targets="human" type="gaze" causeofdeathdescription="" selfcauseofdeathdescription="" isbuff="true" healableinmedicalclinic="false">
		<Effect minstrength="0" maxstrength="2" minscreendistort="0.5" maxscreendistort="0.5" minscreenblur="0.1" maxscreenblur="0.1" minradialdistort="0.5" maxradialdistort="0.5" minchromaticaberration="0.4" maxchromaticaberration="0.4" minskillmultiplier="0.9" maxskillmultiplier="0.9" ></Effect>
		<icon texture="%ModDir%/Textures/AfflictionIcons.png" sourcerect="384,128,128,128"  origin="0,0" />
	</Affliction>
  
			<!-- TERROR EYE -->
	<Affliction iconcolors="255,0,0,255;255,0,0,255" name="" identifier="eyeterror" description="" limbspecific="true" indicatorlimb="Head" showiconthreshold="1" showinhealthscannerthreshold="100" maxstrength="2" targets="human" type="gaze" causeofdeathdescription="" selfcauseofdeathdescription="" isbuff="true" healableinmedicalclinic="false">
		<Effect minstrength="0" maxstrength="2" minskillmultiplier="0.1" maxskillmultiplier="0.1" multiplybymaxvitality="true" minvitalitydecrease="0" maxvitalitydecrease="0.3" minradialdistort="0.0" maxradialdistort="0.5" resistancefor="pressure, damage" minresistance="0" maxresistance="0.5" minscreenblur="0.0" maxscreenblur="0.1">
			<StatValue stattype="WeaponsSkillBonus" value="400" />
			<StatusEffect target="Character" targetlimb="Head">
				<Conditional IsLocalPlayer="True" />
				<Explosion range="1" force="0" smoke="false" sparks="false" flames="false" shockwave="false" underwaterbubble="false" camerashake="5" camerashakerange="250"  screencolor="255,0,0,60" screencolorrange="1000" screencolorduration="0.22" />
				<Sound file="%ModDir%/Sounds/eyesofterror.ogg" loop="false" dontmuffle="true" volume="0.5" />
			</StatusEffect>
		</Effect>
		<icon texture="%ModDir%/Textures/AfflictionIcons.png" sourcerect="0,128,128,128"  origin="0,0" />
	</Affliction>
 	
</Afflictions>
